{
  "fr": {
    "site_name": "Retour de Force",
    "site_tagline": "Mods vérifiés pour BeamNG & Assetto Corsa",
    "hero_title_1": "Mods vérifiés pour",
    "mods_available": "mods disponibles",
    "beamng_sub": "Véhicules, maps, scénarios et configs vérifiés.",
    "assetto_sub": "Voitures, circuits, skins et configs vérifiés.",
    "nav_home": "Accueil",
    "nav_beamng": "BeamNG",
    "nav_assetto": "Assetto Corsa",
    "nav_about": "À propos",
    "nav_stats": "Stats",
    "search_placeholder": "Rechercher un mod...",
    "filter_all": "Tous",
    "filter_game": "Jeu",
    "filter_category": "Catégorie",
    "sort_date": "Date",
    "sort_name": "Nom",
    "card_download": "Télécharger",
    "card_version": "Version",
    "card_updated": "Mis à jour",
    "card_author": "Auteur",
    "card_source": "Source",
    "card_tags": "Tags",
    "detail_download": "Télécharger le mod",
    "detail_back": "← Retour",
    "badge_verified": "Vérifié",
    "no_results": "Aucun mod trouvé.",
    "footer_text": "Tous les mods sont vérifiés via Discord avant publication.",
    "toggle_lang": "EN",
    "stats_total": "Total mods",
    "stats_tags_total": "Tags utilisés",
    "stats_repartition": "Répartition",
    "stats_by_category": "par catégorie",
    "stats_top_tags": "Top tags",
    "stats_latest": "Dernier mod ajouté",
    "nav_soumettre": "Soumettre"
  },
  "en": {
    "site_name": "Force Feedback",
    "site_tagline": "Verified mods for BeamNG & Assetto Corsa",
    "hero_title_1": "Verified mods for",
    "mods_available": "mods available",
    "beamng_sub": "Verified vehicles, maps, scenarios and configs.",
    "assetto_sub": "Verified cars, tracks, skins and configs.",
    "nav_home": "Home",
    "nav_beamng": "BeamNG",
    "nav_assetto": "Assetto Corsa",
    "nav_about": "About",
    "nav_stats": "Stats",
    "search_placeholder": "Search a mod...",
    "filter_all": "All",
    "filter_game": "Game",
    "filter_category": "Category",
    "sort_date": "Date",
    "sort_name": "Name",
    "card_download": "Download",
    "card_version": "Version",
    "card_updated": "Updated",
    "card_author": "Author",
    "card_source": "Source",
    "card_tags": "Tags",
    "detail_download": "Download mod",
    "detail_back": "← Back",
    "badge_verified": "Verified",
    "no_results": "No mods found.",
    "footer_text": "All mods are Discord-verified before publication.",
    "toggle_lang": "FR",
    "stats_total": "Total mods",
    "stats_tags_total": "Tags used",
    "stats_repartition": "Breakdown",
    "stats_by_category": "by category",
    "stats_top_tags": "Top tags",
    "stats_latest": "Latest mod added",
    "nav_soumettre": "Submit"
  }
}
